emoji_scan/__init__.py
emoji_scan/emoji_utils.py
emojiscan-0.1.0.dist-info/LICENSE
emojiscan-0.1.0.dist-info/METADATA
emojiscan-0.1.0.dist-info/WHEEL
emojiscan-0.1.0.dist-info/top_level.txt
emojiscan-0.1.0.dist-info/RECORD
