Metadata-Version: 2.2
Name: emojiscan
Version: 0.1.0
Summary: A Python package to extract unique emojis from text files.
Author-email: frissonitte <frissonite@gmail.com>
License: MIT License
Project-URL: Homepage, https://github.com/frissonitte/emojiscan
Project-URL: Repository, https://github.com/frissonitte/emojiscan
Project-URL: Issues, https://github.com/frissonitte/emojiscan/issues
Classifier: Programming Language :: Python :: 3
Classifier: License :: OSI Approved :: MIT License
Classifier: Operating System :: OS Independent
License-File: LICENSE
Requires-Dist: emoji>=2.0.0
